Workbook

Sheet Peta S2T
A1: Tabel target | B1: Kolom target | C1: Tipe | D1: Sumber | E1: Berkas/tabel | F1: Kolom sumber | G1: Transformasi | H1: Step Pentaho
A2: dim_produk | B2: (kunci lookup) | C2: — | D2: S1 | E2: categories | F2: category_id | G2: Kunci Stream lookup dari products.category_id untuk kategori dan sub_kategori baris inferred (produk yang belum ada di S4). | H2: t20: Stream lookup
A3: dim_produk | B3: kategori | C3: VARCHAR(60) | D3: S1 | E3: categories | F3: parent_category_id | G3: Self-lookup ke categories: kategori = category_name induk (Elektronik, Furnitur, Pakaian); hanya untuk baris inferred. | H3: t20: Stream lookup
A4: dim_produk | B4: sub_kategori | C4: VARCHAR(60) | D4: S1 | E4: categories | F4: category_name | G4: Trim; sub_kategori baris inferred = category_name produk (mis. Smartphone). Sembilan nama sub-kategori S1 sama dengan sub_kategori S4. | H4: t20: Stream lookup
A5: dim_pelanggan | B5: customer_id_web | C5: INT | D5: S1 | E5: customers | F5: customer_id | G5: Langsung; is_pelanggan_web = 'Y'. Juga kunci lookup pelanggan_key di fakta S1. | H5: t14: Table input, Merge join
A6: dim_pelanggan | B6: nama | C6: VARCHAR(120) | D6: S1 | E6: customers | F6: full_name | G6: Trim. Untuk orang yang juga member (HP sama), nama S1 diutamakan karena nama member ditulis kapital. | H6: t14: String operations
A7: (tidak dipakai) | B7: — | C7: — | D7: S1 | E7: customers | F7: email | G7: Data pribadi; tidak dibutuhkan empat pertanyaan (pencocokan pelanggan memakai HP). | H7: —
A8: dim_pelanggan | B8: no_hp_normal | C8: VARCHAR(20) | D8: S1 | E8: customers | F8: phone | G8: Baca sebagai String. Ambil digit, buang awalan 62 atau 0, tambah 0 (+6281234834227 → 081234834227). Kunci gabung dengan member S2: 200 HP sama (customer_id 401–600 = M-0401 s.d. M-0600). | H8: t14: Calculator, Replace in string
A9: dim_pelanggan | B9: gender | C9: CHAR(1) | D9: S1 | E9: customers | F9: gender | G9: Langsung (L/P). Member S2 dan pembeli S3 tidak punya gender → NULL. | H9: t14: Select values
A10: (tidak dipakai) | B10: — | C10: — | D10: S1 | E10: customers | F10: birth_date | G10: Tidak ada analisis usia di empat pertanyaan. | H10: —
A11: (tidak dipakai) | B11: — | C11: — | D11: S1 | E11: customers | F11: registered_at | G11: Tanggal daftar akun tidak dibutuhkan empat pertanyaan. | H11: —
A12: (tidak dipakai) | B12: — | C12: — | D12: S1 | E12: customer_addresses | F12: address_id | G12: Kota pelanggan diambil dari alamat is_primary, bukan alamat kirim per order; ID alamat tidak dibutuhkan. | H12: —
... A154: dim_pelanggan | B154: kota | C154: VARCHAR(60) | D154: Ref | E154: ref_kota.csv | F154: kota_baku | G154: Hasil lookup (12 kota baku) menjadi kota member; juga validasi kota toko di dim_toko_kanal. | H154: t13, t14: Stream lookup

Sheet Kolom target lain
A1: Tabel target | B1: Kolom target | C1: Tipe | D1: Sumber | E1: Berkas/tabel | F1: Kolom sumber | G1: Transformasi | H1: Step Pentaho
A2: fact_penjualan | B2: penjualan_id | C2: BIGINT | D2: DW | E2: — | F2: — | G2: AUTO_INCREMENT oleh MySQL; tidak dikirim dari Pentaho. | H2: —
A3: fact_penjualan | B3: sumber_sistem | C3: CHAR(2) | D3: Konstanta | E3: — | F3: — | G3: 'S1' di t20, 'S2' di t21, 'S3' di t22. Dipakai juga untuk DELETE per sumber sebelum rerun. | H3: t20–t22: Add constants
A4: fact_penjualan | B4: no_baris | C4: SMALLINT | D4: Turunan | E4: mpl_pull_page_*.json | F4: $.records[*].items[*] | G4: Khusus S3: urutan item di dalam items[] per invoice setelah dedup (1 atau 2). | H4: t22: Add value fields changing sequence
A5: fact_penjualan | B5: tanggal_key | C5: INT | D5: Turunan | E5: orders / trx_header_TS*.csv / mpl_pull_page_*.json | F5: order_ts / trx_date / paid_at | G5: Tanggal WIB (S3 sesudah + 7 jam) diformat yyyyMMdd; harus ada di dim_tanggal (FK). | H5: t20–t22: Calculator, Select values
A6: fact_penjualan | B6: toko_kanal_key | C6: INT | D6: Konstanta | E6: — | F6: — | G6: Khusus S1: kode_toko konstanta 'WEB' → lookup dim_toko_kanal (Situs Web). | H6: t20: Add constants, Database lookup
A7: fact_penjualan | B7: waktu_wib | C7: DATETIME | D7: Turunan | E7: trx_header_TS*.csv | F7: trx_date | G7: Khusus S2: tanggal trx_date jam 00:00:00 karena S2 tidak menyimpan jam. | H7: t21: Select values
A8: fact_penjualan | B8: pelanggan_key | C8: INT | D8: Turunan | E8: mpl_pull_page_*.json | F8: $.records[*].buyer.hash | G8: Khusus S3: lookup dim_pelanggan.buyer_hash → pelanggan_key; tidak ketemu → -1. | H8: t22: Database lookup
A9: fact_penjualan | B9: kampanye_key | C9: INT | D9: Turunan | E9: trx_line_TS*.csv, trx_header_TS*.csv | F9: disc_pct, trx_date | G9: Khusus S2: disc_pct = 0 → 0; tanggal di dalam periode kampanye Toko Fisik atau Semua Kanal dengan target_diskon_persen = disc_pct → kampanye itu (kanal spesifik dulu, lalu tgl_mulai terbaru); selain itu → -2 Diskon non-kampanye. | H9: t21: Database join, If field value is null
A10: fact_penjualan | B10: kampanye_key | C10: INT | D10: Turunan | E10: mpl_pull_page_*.json | F10: items[*].voucher, items[*].qty, items[*].price, paid_at | G10: Khusus S3: voucher = 0 → 0; persen = voucher ÷ (qty × price) × 100, tanggal WIB di dalam periode kampanye Marketplace atau Semua Kanal dengan persen sama → kampanye itu (kanal spesifik dulu, lalu tgl_mulai terbaru); selain itu → -2. | H10: t22: Calculator, Database join
A11: fact_penjualan | B11: penjualan_kotor | C11: DECIMAL(18,2) | D11: Turunan | E11: — | F11: qty, harga_satuan | G11: qty × harga_satuan. | H11: t20–t22: Calculator
A12: fact_penjualan | B12: penjualan_bersih | C12: DECIMAL(18,2) | D12: Turunan | E12: — | F12: penjualan_kotor, diskon | G12: penjualan_kotor − diskon. | H12: t20–t22: Calculator
... A56: err_kampanye | B56: waktu_load | C56: DATETIME | D56: DW | E56: — | F56: — | G56: DEFAULT CURRENT_TIMESTAMP (boleh juga diisi Get System Info). | H56: —

Sheet Ringkasan
A1: Kelengkapan peta source-to-target per berkas sumber
A2: Kolom C = jumlah kolom di header berkas sumber (S3: jumlah field daun JSON, termasuk field bersarang), dihitung dari folder Data. Kolom D–F dihitung otomatis dari lembar Peta S2T.
A4: Sumber | B4: Berkas/tabel | C4: Kolom di berkas sumber | D4: Baris di peta | E4: Dipakai | F4: Tidak dipakai | G4: Status
A5: S1 | B5: categories | C5: 3 | D5: =COUNTIFS('Peta S2T'!$D:$D,$A5,'Peta S2T'!$E:$E,$B5) -> 3 | E5: =COUNTIFS('Peta S2T'!$D:$D,$A5,'Peta S2T'!$E:$E,$B5,'Peta S2T'!$A:$A,"<>(tidak dipakai)") -> 3 | F5: =COUNTIFS('Peta S2T'!$D:$D,$A5,'Peta S2T'!$E:$E,$B5,'Peta S2T'!$A:$A,"(tidak dipakai)") -> 0 | G5: =IF(D5=C5,"Lengkap","Cek") -> Lengkap
A6: S1 | B6: customers | C6: 7 | D6: =COUNTIFS('Peta S2T'!$D:$D,$A6,'Peta S2T'!$E:$E,$B6) -> 7 | E6: =COUNTIFS('Peta S2T'!$D:$D,$A6,'Peta S2T'!$E:$E,$B6,'Peta S2T'!$A:$A,"<>(tidak dipakai)") -> 4 | F6: =COUNTIFS('Peta S2T'!$D:$D,$A6,'Peta S2T'!$E:$E,$B6,'Peta S2T'!$A:$A,"(tidak dipakai)") -> 3 | G6: =IF(D6=C6,"Lengkap","Cek") -> Lengkap
A7: S1 | B7: customer_addresses | C7: 8 | D7: =COUNTIFS('Peta S2T'!$D:$D,$A7,'Peta S2T'!$E:$E,$B7) -> 8 | E7: =COUNTIFS('Peta S2T'!$D:$D,$A7,'Peta S2T'!$E:$E,$B7,'Peta S2T'!$A:$A,"<>(tidak dipakai)") -> 3 | F7: =COUNTIFS('Peta S2T'!$D:$D,$A7,'Peta S2T'!$E:$E,$B7,'Peta S2T'!$A:$A,"(tidak dipakai)") -> 5 | G7: =IF(D7=C7,"Lengkap","Cek") -> Lengkap
A8: S1 | B8: products | C8: 7 | D8: =COUNTIFS('Peta S2T'!$D:$D,$A8,'Peta S2T'!$E:$E,$B8) -> 7 | E8: =COUNTIFS('Peta S2T'!$D:$D,$A8,'Peta S2T'!$E:$E,$B8,'Peta S2T'!$A:$A,"<>(tidak dipakai)") -> 4 | F8: =COUNTIFS('Peta S2T'!$D:$D,$A8,'Peta S2T'!$E:$E,$B8,'Peta S2T'!$A:$A,"(tidak dipakai)") -> 3 | G8: =IF(D8=C8,"Lengkap","Cek") -> Lengkap
A9: S1 | B9: vouchers | C9: 8 | D9: =COUNTIFS('Peta S2T'!$D:$D,$A9,'Peta S2T'!$E:$E,$B9) -> 8 | E9: =COUNTIFS('Peta S2T'!$D:$D,$A9,'Peta S2T'!$E:$E,$B9,'Peta S2T'!$A:$A,"<>(tidak dipakai)") -> 3 | F9: =COUNTIFS('Peta S2T'!$D:$D,$A9,'Peta S2T'!$E:$E,$B9,'Peta S2T'!$A:$A,"(tidak dipakai)") -> 5 | G9: =IF(D9=C9,"Lengkap","Cek") -> Lengkap
A10: S1 | B10: orders | C10: 8 | D10: =COUNTIFS('Peta S2T'!$D:$D,$A10,'Peta S2T'!$E:$E,$B10) -> 8 | E10: =COUNTIFS('Peta S2T'!$D:$D,$A10,'Peta S2T'!$E:$E,$B10,'Peta S2T'!$A:$A,"<>(tidak dipakai)") -> 5 | F10: =COUNTIFS('Peta S2T'!$D:$D,$A10,'Peta S2T'!$E:$E,$B10,'Peta S2T'!$A:$A,"(tidak dipakai)") -> 3 | G10: =IF(D10=C10,"Lengkap","Cek") -> Lengkap
A11: S1 | B11: order_items | C11: 8 | D11: =COUNTIFS('Peta S2T'!$D:$D,$A11,'Peta S2T'!$E:$E,$B11) -> 8 | E11: =COUNTIFS('Peta S2T'!$D:$D,$A11,'Peta S2T'!$E:$E,$B11,'Peta S2T'!$A:$A,"<>(tidak dipakai)") -> 7 | F11: =COUNTIFS('Peta S2T'!$D:$D,$A11,'Peta S2T'!$E:$E,$B11,'Peta S2T'!$A:$A,"(tidak dipakai)") -> 1 | G11: =IF(D11=C11,"Lengkap","Cek") -> Lengkap
A12: S1 | B12: order_status_history | C12: 4 | D12: =COUNTIFS('Peta S2T'!$D:$D,$A12,'Peta S2T'!$E:$E,$B12) -> 4 | E12: =COUNTIFS('Peta S2T'!$D:$D,$A12,'Peta S2T'!$E:$E,$B12,'Peta S2T'!$A:$A,"<>(tidak dipakai)") -> 0 | F12: =COUNTIFS('Peta S2T'!$D:$D,$A12,'Peta S2T'!$E:$E,$B12,'Peta S2T'!$A:$A,"(tidak dipakai)") -> 4 | G12: =IF(D12=C12,"Lengkap","Cek") -> Lengkap
A13: S1 | B13: payments | C13: 6 | D13: =COUNTIFS('Peta S2T'!$D:$D,$A13,'Peta S2T'!$E:$E,$B13) -> 6 | E13: =COUNTIFS('Peta S2T'!$D:$D,$A13,'Peta S2T'!$E:$E,$B13,'Peta S2T'!$A:$A,"<>(tidak dipakai)") -> 0 | F13: =COUNTIFS('Peta S2T'!$D:$D,$A13,'Peta S2T'!$E:$E,$B13,'Peta S2T'!$A:$A,"(tidak dipakai)") -> 6 | G13: =IF(D13=C13,"Lengkap","Cek") -> Lengkap
A14: S1 | B14: shipments | C14: 6 | D14: =COUNTIFS('Peta S2T'!$D:$D,$A14,'Peta S2T'!$E:$E,$B14) -> 6 | E14: =COUNTIFS('Peta S2T'!$D:$D,$A14,'Peta S2T'!$E:$E,$B14,'Peta S2T'!$A:$A,"<>(tidak dipakai)") -> 0 | F14: =COUNTIFS('Peta S2T'!$D:$D,$A14,'Peta S2T'!$E:$E,$B14,'Peta S2T'!$A:$A,"(tidak dipakai)") -> 6 | G14: =IF(D14=C14,"Lengkap","Cek") -> Lengkap
A15: S1 | B15: order_returns | C15: 7 | D15: =COUNTIFS('Peta S2T'!$D:$D,$A15,'Peta S2T'!$E:$E,$B15) -> 7 | E15: =COUNTIFS('Peta S2T'!$D:$D,$A15,'Peta S2T'!$E:$E,$B15,'Peta S2T'!$A:$A,"<>(tidak dipakai)") -> 3 | F15: =COUNTIFS('Peta S2T'!$D:$D,$A15,'Peta S2T'!$E:$E,$B15,'Peta S2T'!$A:$A,"(tidak dipakai)") -> 4 | G15: =IF(D15=C15,"Lengkap","Cek") -> Lengkap
A16: S2 | B16: store_master.csv | C16: 7 | D16: =COUNTIFS('Peta S2T'!$D:$D,$A16,'Peta S2T'!$E:$E,$B16) -> 7 | E16: =COUNTIFS('Peta S2T'!$D:$D,$A16,'Peta S2T'!$E:$E,$B16,'Peta S2T'!$A:$A,"<>(tidak dipakai)") -> 5 | F16: =COUNTIFS('Peta S2T'!$D:$D,$A16,'Peta S2T'!$E:$E,$B16,'Peta S2T'!$A:$A,"(tidak dipakai)") -> 2 | G16: =IF(D16=C16,"Lengkap","Cek") -> Lengkap
... A28: Ref | B28: ref_kota.csv | C28: 2 | D28: =COUNTIFS('Peta S2T'!$D:$D,$A28,'Peta S2T'!$E:$E,$B28) -> 2 | E28: =COUNTIFS('Peta S2T'!$D:$D,$A28,'Peta S2T'!$E:$E,$B28,'Peta S2T'!$A:$A,"<>(tidak dipakai)") -> 2 | F28: =COUNTIFS('Peta S2T'!$D:$D,$A28,'Peta S2T'!$E:$E,$B28,'Peta S2T'!$A:$A,"(tidak dipakai)") -> 0 | G28: =IF(D28=C28,"Lengkap","Cek") -> Lengkap
A29: Total | B29: Semua berkas di folder Data | C29: =SUM(C5:C28) -> 153 | D29: =SUM(D5:D28) -> 153 | E29: =SUM(E5:E28) -> 88 | F29: =SUM(F5:F28) -> 65 | G29: =IF(AND(D29=C29,COUNTA('Peta S2T'!F:F)-1=C29),"Lengkap","Cek") -> Lengkap
A31: Sumber | B31: Kolom di berkas sumber | C31: Baris di peta | D31: Dipakai | E31: Tidak dipakai
A32: S1 | B32: =SUMIFS(C$5:C$28,$A$5:$A$28,$A32) -> 72 | C32: =SUMIFS(D$5:D$28,$A$5:$A$28,$A32) -> 72 | D32: =SUMIFS(E$5:E$28,$A$5:$A$28,$A32) -> 32 | E32: =SUMIFS(F$5:F$28,$A$5:$A$28,$A32) -> 40
A33: S2 | B33: =SUMIFS(C$5:C$28,$A$5:$A$28,$A33) -> 39 | C33: =SUMIFS(D$5:D$28,$A$5:$A$28,$A33) -> 39 | D33: =SUMIFS(E$5:E$28,$A$5:$A$28,$A33) -> 22 | E33: =SUMIFS(F$5:F$28,$A$5:$A$28,$A33) -> 17
A34: S3 | B34: =SUMIFS(C$5:C$28,$A$5:$A$28,$A34) -> 14 | C34: =SUMIFS(D$5:D$28,$A$5:$A$28,$A34) -> 14 | D34: =SUMIFS(E$5:E$28,$A$5:$A$28,$A34) -> 12 | E34: =SUMIFS(F$5:F$28,$A$5:$A$28,$A34) -> 2
A35: S4 | B35: =SUMIFS(C$5:C$28,$A$5:$A$28,$A35) -> 18 | C35: =SUMIFS(D$5:D$28,$A$5:$A$28,$A35) -> 18 | D35: =SUMIFS(E$5:E$28,$A$5:$A$28,$A35) -> 12 | E35: =SUMIFS(F$5:F$28,$A$5:$A$28,$A35) -> 6
A36: S5 | B36: =SUMIFS(C$5:C$28,$A$5:$A$28,$A36) -> 8 | C36: =SUMIFS(D$5:D$28,$A$5:$A$28,$A36) -> 8 | D36: =SUMIFS(E$5:E$28,$A$5:$A$28,$A36) -> 8 | E36: =SUMIFS(F$5:F$28,$A$5:$A$28,$A36) -> 0
A37: Ref | B37: =SUMIFS(C$5:C$28,$A$5:$A$28,$A37) -> 2 | C37: =SUMIFS(D$5:D$28,$A$5:$A$28,$A37) -> 2 | D37: =SUMIFS(E$5:E$28,$A$5:$A$28,$A37) -> 2 | E37: =SUMIFS(F$5:F$28,$A$5:$A$28,$A37) -> 0

Sheet Petunjuk
A1: Peta source-to-target (Deliverable 3.1.3) — Data Warehouse NRG
A3: Isi berkas
A4: Peta S2T: satu baris untuk setiap kolom sumber di folder Data (S1 11 tabel, S2 7 jenis berkas, S3 semua field JSON, S4 3 berkas, S5, ref_kota).
A5: Kolom target lain: kolom target yang tidak muncul di lembar Peta S2T, yaitu hasil hitung, dibangkitkan Pentaho atau MySQL, konstanta, atau target kedua dari kolom sumber yang sama; bersama Peta S2T, setiap kolom nrg_dw_ddl.sql punya asal-usul.
A6: Ringkasan: cek otomatis jumlah kolom per berkas; Status harus "Lengkap" untuk semua baris.
A8: Arti kolom
A9: Tabel target, Kolom target, Tipe: tabel dan kolom di 02_ddl/nrg_dw_ddl.sql beserta tipenya.
A10: Sumber: S1 ECOM_DB, S2 POS_TOKO, S3 MPL_API, S4 ERP_MASTER, S5 MKT_SHEET, Ref ref_kota.
A11: Berkas/tabel dan Kolom sumber: nama persis seperti di berkas sumber; S3 memakai JSONPath ($.records[*]...).
A12: Transformasi: aturan pembersihan dan perhitungan (Tahap 3 dan 4 dokumen panduan) beserta angka buktinya.
A13: Step Pentaho: kode transformasi (t01–t30) dan step utama yang menjalankan aturan.
A15: Penanda khusus di Kolom target
... A34: Atribusi kampanye toko dan marketplace: tanggal masuk periode kampanye kanalnya atau Semua Kanal dengan persen sama; kanal spesifik dulu, lalu tgl_mulai terbaru.
